Ysrmaking/String_tool.py
Ysrmaking/__init__.py
Ysrmaking/algorithm.py
Ysrmaking/array_tool.py
Ysrmaking/yuanshiren.py
Ysrmaking/zip_tool.py
Ysrmaking-1.0.6.dist-info/METADATA
Ysrmaking-1.0.6.dist-info/WHEEL
Ysrmaking-1.0.6.dist-info/top_level.txt
Ysrmaking-1.0.6.dist-info/RECORD
